beiker_base_tools/__init__.py
beiker_base_tools/beiker_base_tools.py
beiker_base_tools-1.0.1.dist-info/METADATA
beiker_base_tools-1.0.1.dist-info/WHEEL
beiker_base_tools-1.0.1.dist-info/top_level.txt
beiker_base_tools-1.0.1.dist-info/RECORD
