Metadata-Version: 2.1
Name: beiker_base_tools
Version: 1.0.1
Requires-Dist: pandas
Requires-Dist: mysql-connector-python
Requires-Dist: pillow
